picam_iot/__init__.py
picam_iot/cli.py
picam_iot/image.py
picam_iot/picam_iot.py
picam_iot/storage.py
picam_iot/video.py
picam_iot-0.1.0.dist-info/AUTHORS.rst
picam_iot-0.1.0.dist-info/LICENSE
picam_iot-0.1.0.dist-info/METADATA
picam_iot-0.1.0.dist-info/WHEEL
picam_iot-0.1.0.dist-info/entry_points.txt
picam_iot-0.1.0.dist-info/top_level.txt
picam_iot-0.1.0.dist-info/RECORD
