Metadata-Version: 1.2
Name: picam_iot
Version: 0.1.0
Summary: picam_iot provides simple interfacing with the picam V2 and intergrates it with Python computer vision or image processing libraries.
Home-page: https://github.com/lindelanimcebo/picam_iot
Author: Lindelani Mbatha
Author-email: lindelanimcebo@gmail.com
License: MIT license
Keywords: picam_iot
Platform: UNKNOWN
Classifier: Development Status :: 2 - Pre-Alpha
Classifier: Intended Audience :: Developers
Classifier: License :: OSI Approved :: MIT License
Classifier: Natural Language :: English
Classifier: Programming Language :: Python :: 3
Classifier: Programming Language :: Python :: 3.5
Classifier: Programming Language :: Python :: 3.6
Classifier: Programming Language :: Python :: 3.7
Classifier: Programming Language :: Python :: 3.8
Requires-Python: >=3.5
